cibuildwheel/__init__.py
cibuildwheel/__main__.py
cibuildwheel/architecture.py
cibuildwheel/bashlex_eval.py
cibuildwheel/environment.py
cibuildwheel/extra.py
cibuildwheel/linux.py
cibuildwheel/logger.py
cibuildwheel/macos.py
cibuildwheel/oci_container.py
cibuildwheel/options.py
cibuildwheel/projectfiles.py
cibuildwheel/py.typed
cibuildwheel/schema.py
cibuildwheel/typing.py
cibuildwheel/util.py
cibuildwheel/windows.py
cibuildwheel/_compat/__init__.py
cibuildwheel/_compat/tomllib.py
cibuildwheel/_compat/typing.py
cibuildwheel/resources/build-platforms.toml
cibuildwheel/resources/build-platforms.toml.bak
cibuildwheel/resources/cibuildwheel.schema.json
cibuildwheel/resources/constraints-python310.txt
cibuildwheel/resources/constraints-python311.txt
cibuildwheel/resources/constraints-python312.txt
cibuildwheel/resources/constraints-python36.txt
cibuildwheel/resources/constraints-python37.txt
cibuildwheel/resources/constraints-python38.txt
cibuildwheel/resources/constraints-python39.txt
cibuildwheel/resources/constraints.in
cibuildwheel/resources/constraints.txt
cibuildwheel/resources/defaults.toml
cibuildwheel/resources/install_certifi.py
cibuildwheel/resources/pinned_docker_images.cfg
cibuildwheel/resources/testing_temp_dir_file.py
cibuildwheel/resources/virtualenv.toml
cibuildwheel_cn-2.16.2.1.dist-info/LICENSE
cibuildwheel_cn-2.16.2.1.dist-info/METADATA
cibuildwheel_cn-2.16.2.1.dist-info/WHEEL
cibuildwheel_cn-2.16.2.1.dist-info/entry_points.txt
cibuildwheel_cn-2.16.2.1.dist-info/top_level.txt
cibuildwheel_cn-2.16.2.1.dist-info/RECORD
